README.rst
setup.cfg
setup.py
browserplus/__init__.py
browserplus/browserplus.py
browserplus.egg-info/PKG-INFO
browserplus.egg-info/SOURCES.txt
browserplus.egg-info/dependency_links.txt
browserplus.egg-info/not-zip-safe
browserplus.egg-info/requires.txt
browserplus.egg-info/top_level.txt