Metadata-Version: 1.1
Name: browserplus
Version: 0.0.1
Summary: Advanced Mechanize browser.
Home-page: https://github.com/vinceau/browserplus
Author: Vince Au
Author-email: vinceau09@gmail.com
License: MIT
Platform: any
Classifier: Development Status :: 5 - Production/Stable
Classifier: Environment :: Web Environment
Classifier: Intended Audience :: Developers
Classifier: License :: OSI Approved :: MIT License
Classifier: Operating System :: OS Independent
Classifier: Programming Language :: Python
Classifier: Topic :: Internet :: WWW/HTTP :: Dynamic Content
Classifier: Topic :: Software Development :: Libraries :: Python Modules
